.dockerignore
.editorconfig
CONTRIBUTING.rst
INSTALL.rst
LICENSE
MANIFEST.in
README.rst
babel.ini
pytest.ini
requirements-devel.txt
requirements.txt
run-tests.sh
setup.cfg
setup.py
.tx/config
docs/Makefile
docs/api.rst
docs/authors.rst
docs/changes.rst
docs/conf.py
docs/contributing.rst
docs/index.rst
docs/installation.rst
docs/license.rst
docs/make.bat
docs/usage.rst
examples/app.py
invenio_workflows_files/__init__.py
invenio_workflows_files/api.py
invenio_workflows_files/ext.py
invenio_workflows_files/models.py
invenio_workflows_files.egg-info/PKG-INFO
invenio_workflows_files.egg-info/SOURCES.txt
invenio_workflows_files.egg-info/dependency_links.txt
invenio_workflows_files.egg-info/entry_points.txt
invenio_workflows_files.egg-info/not-zip-safe
invenio_workflows_files.egg-info/requires.txt
invenio_workflows_files.egg-info/top_level.txt
invenio_workflows_files/alembic/3255c6f9aca0_introducing_invenio_workflows_files_models.py
invenio_workflows_files/alembic/__init__.py
invenio_workflows_files/templates/invenio_workflows_files/base.html
invenio_workflows_files/templates/invenio_workflows_files/index.html
tests/conftest.py
tests/test_invenio_workflows_files.py