Metadata-Version: 2.1
Name: invenio-workflows-files
Version: 1.0.1
Summary: Invenio module adding invenio-files-rest integration to invenio-workflows.
